odoo9_addon_partner_phonecall_schedule-9.0.1.1.0-py2.7-nspkg.pth
odoo9_addon_partner_phonecall_schedule-9.0.1.1.0.dist-info/DESCRIPTION.rst
odoo9_addon_partner_phonecall_schedule-9.0.1.1.0.dist-info/METADATA
odoo9_addon_partner_phonecall_schedule-9.0.1.1.0.dist-info/RECORD
odoo9_addon_partner_phonecall_schedule-9.0.1.1.0.dist-info/WHEEL
odoo9_addon_partner_phonecall_schedule-9.0.1.1.0.dist-info/metadata.json
odoo9_addon_partner_phonecall_schedule-9.0.1.1.0.dist-info/namespace_packages.txt
odoo9_addon_partner_phonecall_schedule-9.0.1.1.0.dist-info/top_level.txt
odoo_addons/partner_phonecall_schedule/README.rst
odoo_addons/partner_phonecall_schedule/__init__.py
odoo_addons/partner_phonecall_schedule/__openerp__.py
odoo_addons/partner_phonecall_schedule/i18n/es.po
odoo_addons/partner_phonecall_schedule/models/__init__.py
odoo_addons/partner_phonecall_schedule/models/res_partner.py
odoo_addons/partner_phonecall_schedule/security/ir.model.access.csv
odoo_addons/partner_phonecall_schedule/static/description/icon.png
odoo_addons/partner_phonecall_schedule/tests/__init__.py
odoo_addons/partner_phonecall_schedule/tests/test_schedule.py
odoo_addons/partner_phonecall_schedule/views/res_partner_view.xml
