Metadata-Version: 2.0
Name: odoo9-addon-partner-phonecall-schedule
Version: 9.0.1.1.0
Summary: Track the time and days your partners expect phone calls
Home-page: https://github.com/OCA/crm
Author: Tecnativa, Odoo Community Association (OCA)
Author-email: support@odoo-community.org
License: AGPL-3
Platform: UNKNOWN
Classifier: Programming Language :: Python :: 2.7
Classifier: Framework :: Odoo
Classifier: License :: OSI Approved :: GNU Affero General Public License v3
Requires-Dist: odoo (<9.1a,>=9.0a)
